azureml/__init__.py
azureml/pipeline/__init__.py
azureml/pipeline/steps/__init__.py
azureml/pipeline/steps/_hdinsight_step.py
azureml/pipeline/steps/adla_step.py
azureml/pipeline/steps/automl_step.py
azureml/pipeline/steps/azurebatch_step.py
azureml/pipeline/steps/command_step.py
azureml/pipeline/steps/data_transfer_step.py
azureml/pipeline/steps/databricks_step.py
azureml/pipeline/steps/estimator_step.py
azureml/pipeline/steps/hyper_drive_step.py
azureml/pipeline/steps/kusto_step.py
azureml/pipeline/steps/module_step.py
azureml/pipeline/steps/mpi_step.py
azureml/pipeline/steps/parallel_run_config.py
azureml/pipeline/steps/parallel_run_step.py
azureml/pipeline/steps/python_script_step.py
azureml/pipeline/steps/r_script_step.py
azureml/pipeline/steps/synapse_spark_step.py
azureml_pipeline_steps-1.60.0.dist-info/licenses/LICENSE.txt
azureml_pipeline_steps-1.60.0.dist-info/METADATA
azureml_pipeline_steps-1.60.0.dist-info/WHEEL
azureml_pipeline_steps-1.60.0.dist-info/top_level.txt
azureml_pipeline_steps-1.60.0.dist-info/RECORD
